{
  "settings": {
    "max_per_day": 3,
    "max_same_subject_per_day": 2,
    "lang": "pl"
  },
  "exams": [
    {
      "id": "exam_past_1",
      "subject": "Fizyka",
      "title": "Egzamin pisemny",
      "date": "2026-01-15"
    },
    {
      "id": "exam_past_2",
      "subject": "Chemia",
      "title": "Kolokwium",
      "date": "2026-01-20"
    },
    {
      "id": "exam_urgent",
      "subject": "Statystyka",
      "title": "Egzamin Zerowy",
      "date": "2026-01-24"
    },
    {
      "id": "exam_9f2a7b30",
      "subject": "Matematyka",
      "title": "Zaliczenie",
      "date": "2026-01-30"
    },
    {
      "id": "exam_4d6e81fa",
      "subject": "Angielski",
      "title": "Egzamin ustny",
      "date": "2026-02-05"
    },
    {
      "id": "exam_b2c944d7",
      "subject": "Informatyka",
      "title": "Obrona projektu",
      "date": "2026-02-12"
    }
  ],
  "topics": [
    {
      "id": "topic_done_1",
      "exam_id": "exam_past_1",
      "name": "Kinematyka",
      "status": "done",
      "scheduled_date": "2026-01-10",
      "locked": true
    },
    {
      "id": "topic_done_2",
      "exam_id": "exam_past_2",
      "name": "Wiązania chemiczne",
      "status": "done",
      "scheduled_date": "2026-01-18",
      "locked": true
    },
    {
      "id": "topic_math_done",
      "exam_id": "exam_9f2a7b30",
      "name": "Liczby zespolone",
      "status": "done",
      "scheduled_date": "2026-01-21",
      "locked": true
    },
    {
      "id": "topic_stat_done",
      "exam_id": "exam_urgent",
      "name": "Prawdopodobieństwo",
      "status": "done",
      "scheduled_date": "2026-01-22",
      "locked": true
    },
    {
      "id": "topic_OVERDUE",
      "exam_id": "exam_9f2a7b30",
      "name": "Macierze i wyznaczniki",
      "status": "todo",
      "scheduled_date": "2026-01-22",
      "locked": false
    },
    {
      "id": "topic_TODAY_1",
      "exam_id": "exam_urgent",
      "name": "Rozkłady zmiennych",
      "status": "done",
      "scheduled_date": "2026-01-23",
      "locked": false
    },
    {
      "id": "topic_TODAY_2",
      "exam_id": "exam_urgent",
      "name": "Testy hipotez",
      "status": "done",
      "scheduled_date": "2026-01-23",
      "locked": false
    },
    {
      "id": "topic_TODAY_3",
      "exam_id": "exam_9f2a7b30",
      "name": "Ciągi liczbowe",
      "status": "todo",
      "scheduled_date": "2026-01-23",
      "locked": false
    },
    {
      "id": "topic_future_1",
      "exam_id": "exam_9f2a7b30",
      "name": "Granice funkcji",
      "status": "todo",
      "scheduled_date": "2026-01-25",
      "locked": false
    },
    {
      "id": "topic_future_2",
      "exam_id": "exam_4d6e81fa",
      "name": "Słownictwo - Business",
      "status": "done",
      "scheduled_date": "2026-01-26",
      "locked": false
    },
    {
      "id": "topic_future_3",
      "exam_id": "exam_9f2a7b30",
      "name": "Pochodne",
      "status": "todo",
      "scheduled_date": "2026-01-26",
      "locked": false
    },
    {
      "id": "topic_future_4",
      "exam_id": "exam_4d6e81fa",
      "name": "Czasy przeszłe",
      "status": "todo",
      "scheduled_date": "2026-01-27",
      "locked": false
    },
    {
      "id": "topic_future_5",
      "exam_id": "exam_9f2a7b30",
      "name": "Całki nieoznaczone",
      "status": "todo",
      "scheduled_date": "2026-01-27",
      "locked": false
    },
    {
      "id": "topic_future_6",
      "exam_id": "exam_b2c944d7",
      "name": "Struktura bazy danych",
      "status": "todo",
      "scheduled_date": "2026-01-28",
      "locked": false
    },
    {
      "id": "topic_future_7",
      "exam_id": "exam_9f2a7b30",
      "name": "Funkcje Cyklometryczne",
      "status": "todo",
      "scheduled_date": "2026-01-28",
      "locked": false
    }
  ]
}